diop/__init__.py
diop/adapters/__init__.py
diop/adapters/activedirectory.py
diop/adapters/ppms.py
diop/adapters/psytricks.py
diop/admin.py
diop/apps.py
diop/decorators.py
diop/exceptions.py
diop/fixtures/messagetemplate.yaml
diop/fixtures/sites.yaml
diop/management/__init__.py
diop/management/commands/__init__.py
diop/management/commands/gen_unitfiles.py
diop/management/commands/pdoc.py
diop/management/commands/populate_db.py
diop/management/commands/register_tasks.py
diop/management/commands/setup_groups.py
diop/migrations/0001_initial.py
diop/migrations/0002_machine.py
diop/migrations/0003_alter_siteconfig_options_alter_machine_fqdn_and_more.py
diop/migrations/0004_deliverygroup.py
diop/migrations/0005_machine_deliverygroup.py
diop/migrations/0006_alter_deliverygroup_booking_required_and_more.py
diop/migrations/0007_deliverygroup_access_users.py
diop/migrations/0008_session_sessionproperties.py
diop/migrations/0009_alter_session_user.py
diop/migrations/0010_machine_agent.py
diop/migrations/0011_task_issue.py
diop/migrations/0012_machine_active_machine_updated.py
diop/migrations/0013_alter_issue_description_alter_issue_resolved_and_more.py
diop/migrations/0014_session_updated.py
diop/migrations/0015_rename_session_fqdn_session_machine.py
diop/migrations/0016_notification.py
diop/migrations/0017_alter_machine_deliverygroup_alter_machine_state.py
diop/migrations/0018_machine_req_maintenance.py
diop/migrations/0019_user_disconnected_max_alter_user_accessgroup_member_and_more.py
diop/migrations/0020_reservation_ppmsbooking_and_more.py
diop/migrations/0021_alter_issue_description_alter_issue_task_and_more.py
diop/migrations/0022_alter_notification_body_alter_task_description.py
diop/migrations/0023_sitelog.py
diop/migrations/0024_alter_sitelog_deliverygroup_alter_sitelog_machine_and_more.py
diop/migrations/0025_alter_user_department_alter_user_fullname_and_more.py
diop/migrations/0026_remove_user_active_user_enabled.py
diop/migrations/0027_delete_siteconfig.py
diop-0.4.0a36.dist-info/METADATA
diop-0.4.0a36.dist-info/WHEEL
diop-0.4.0a36.dist-info/entry_points.txt
diop-0.4.0a36.dist-info/RECORD
